authcore/__init__.py
authcore/config.py
authcore/contracts.py
authcore/jwt_service.py
authcore/oauth_service.py
authcore/passwords.py
authcore/permission_decorator.py
authcore/rbac_services.py
authcore/run.py
authcore/session_service.py
authcore/store_backends.py
authcore/two_factor_auth_service.py
authcore/utils.py
authcore/adapters/__init__.py
authcore/adapters/django_adapter.py
authcore/adapters/fastapi_adapter.py
authcore/adapters/flask_adapter.py
flycatch_authcore-0.1.0.dist-info/licenses/LICENSE
flycatch_authcore-0.1.0.dist-info/METADATA
flycatch_authcore-0.1.0.dist-info/WHEEL
flycatch_authcore-0.1.0.dist-info/top_level.txt
flycatch_authcore-0.1.0.dist-info/RECORD
