Metadata-Version: 2.4
Name: flycatch-authcore
Version: 0.1.0
Summary: AuthCore: JWT/Session/OAuth core with adapters for FastAPI, Flask, and Django
Author-email: AuthCore Team <support@flycatch.tech>
License-Expression: GPL-3.0-or-later
Keywords: authentication,jwt,oauth2,session,fastapi,django,flask
Classifier: Development Status :: 5 - Production/Stable
Classifier: Programming Language :: Python :: 3
Classifier: Operating System :: OS Independent
Classifier: Framework :: FastAPI
Classifier: Framework :: Flask
Classifier: Framework :: Django
Classifier: Topic :: Software Development :: Libraries :: Application Frameworks
Classifier: Topic :: Security
Classifier: Topic :: Internet :: WWW/HTTP
Classifier: Topic :: Software Development :: Libraries
Requires-Python: <4.0,>=3.10
License-File: LICENSE
Requires-Dist: PyJWT<3.0,>=2.9
Requires-Dist: anyio<5.0,>=4.3
Requires-Dist: httpx<0.29,>=0.27
Requires-Dist: passlib[bcrypt]<2.0,>=1.7.4
Requires-Dist: bcrypt<5.0,>=4.1.2
Requires-Dist: pydantic<3.0,>=2.4
Provides-Extra: fastapi
Requires-Dist: fastapi<0.117,>=0.111; extra == "fastapi"
Requires-Dist: uvicorn<0.36,>=0.24; extra == "fastapi"
Requires-Dist: starlette<0.41,>=0.37; extra == "fastapi"
Provides-Extra: flask
Requires-Dist: Flask<4.0,>=2.3; extra == "flask"
Requires-Dist: authlib<2.0,>=1.3; extra == "flask"
Provides-Extra: django
Requires-Dist: Django<5.0,>=3.2; extra == "django"
Requires-Dist: django-cors-headers<5.0,>=4.3; extra == "django"
Provides-Extra: oauth
Requires-Dist: authlib<2.0,>=1.3; extra == "oauth"
Requires-Dist: starlette<0.41,>=0.37; extra == "oauth"
Provides-Extra: redis
Requires-Dist: redis<6.0,>=5.0; extra == "redis"
Dynamic: license-file
